HDA/__init__.py
HDA/demo.py
HDA/gradient_logger_try.py
HDA/image_utils.py
HDA/test.py
HDA/train.py
HDA/models/Inception.py
HDA/models/__init__.py
HDA/models/autoencoder.py
HDA/models/cbam.py
HDA/models/resnet18.py
HDA/models/resnet50.py
HDA/preprocessing/__init__.py
HDA/preprocessing/data_augmentation.py
HDA/preprocessing/image_pre_processing.py
HDA/preprocessing/image_utils.py
archived/__init__.py
archived/format_csv.py
archived/xlsx_to_csv.py
Human_Data_Analytics-1.0.2.dist-info/METADATA
Human_Data_Analytics-1.0.2.dist-info/WHEEL
Human_Data_Analytics-1.0.2.dist-info/top_level.txt
Human_Data_Analytics-1.0.2.dist-info/RECORD
