Metadata-Version: 2.1
Name: Human_Data_Analytics
Version: 1.0.2
Summary: A brief description of your package
Home-page: https://github.com/cesarbid/Human-Data-Analytics
Author: Cesare Bidini, Nicolò Rinaldi
Author-email: your.email@example.com
Classifier: Programming Language :: Python :: 3
Classifier: License :: OSI Approved :: MIT License
Classifier: Operating System :: OS Independent
Requires-Python: >=3.6
